auto_api/__init__.py
auto_api/__main__.py
auto_api/auth.py
auto_api/config.py
auto_api/exceptions.py
auto_api/messages.py
auto_api/mongodb.py
auto_api/operations.py
auto_api/utils.py
auto_api/validations.py
auto_api/views.py
tests/views/__init__.py
tests/views/test_delete.py
tests/views/test_get.py
tests/views/test_patch.py
tests/views/test_post.py
tests/views/test_put.py
auto_api-2.2.2.dist-info/LICENSE
auto_api-2.2.2.dist-info/METADATA
auto_api-2.2.2.dist-info/WHEEL
auto_api-2.2.2.dist-info/entry_points.txt
auto_api-2.2.2.dist-info/top_level.txt
auto_api-2.2.2.dist-info/RECORD
