Metadata-Version: 2.1
Name: auto-api
Version: 2.2.2
Summary: Automatic Web API REST
Home-page: https://github.com/fvalverd/AutoApi
Author: Felipe Valverde Campos
Author-email: felipe.valverde.campos@gmail.com
License: MIT license
Download-URL: https://github.com/fvalverd/AutoApi/tarball/v2.2.2
Project-URL: Source, https://github.com/fvalverd/AutoApi
Project-URL: Tracker, https://github.com/fvalverd/AutoApi/issues
Keywords: api rest authentication mongodb automatic web flask json python
Platform: UNKNOWN
Classifier: Environment :: Web Environment
Classifier: Environment :: Console
Classifier: Intended Audience :: Developers
Classifier: License :: OSI Approved :: MIT License
Classifier: Operating System :: POSIX
Classifier: Programming Language :: Python
Classifier: Programming Language :: Python :: 2
Classifier: Programming Language :: Python :: 2.7
Classifier: Programming Language :: Python :: 3
Classifier: Programming Language :: Python :: 3.6
Classifier: Programming Language :: Python :: 3.7
Classifier: Programming Language :: Python :: 3.8
Classifier: Topic :: Internet :: WWW/HTTP :: Dynamic Content
Classifier: Topic :: Internet :: WWW/HTTP :: WSGI :: Application
Classifier: Topic :: Software Development :: Libraries :: Application Frameworks
Classifier: Topic :: Software Development :: Libraries :: Python Modules
Requires-Python: !=3.0.*,!=3.1.*,!=3.2.*,!=3.3.*,!=3.4.*,!=3.5.*,>=2.7
Requires-Dist: click (>=6.7)
Requires-Dist: Flask (>=1.0.2)
Requires-Dist: Flask-Cors (>=3.0.7)
Requires-Dist: pymongo (<4,>=3.7.2)
